pyolite
tests
