Metadata-Version: 1.1
Name: baguette-olite
Version: 0.12
Summary: Python wrapper for gitolite
Home-page: https://github.com/baguette-io/baguette-olite/
Author: UNKNOWN
Author-email: pydavid@baguette.io
License: UNKNOWN
Keywords: git,gitolite
Platform: UNKNOWN
Classifier: Intended Audience :: Developers
Classifier: Intended Audience :: System Administrators
Classifier: License :: OSI Approved :: BSD License
Classifier: Programming Language :: Python :: 2.7
Classifier: Programming Language :: Python :: 3.6
